LICENSE
README.md
setup.py
src/example_package_serly.egg-info/PKG-INFO
src/example_package_serly.egg-info/SOURCES.txt
src/example_package_serly.egg-info/dependency_links.txt
src/example_package_serly.egg-info/top_level.txt
src/mathematic_serly/__init__.py
src/mathematic_serly/aritmatika.py
src/mathematic_serly/bangun.py