Metadata-Version: 2.1
Name: example-package-serly
Version: 0.1.1
Summary: Matematika untuk Python
Home-page: https://github.com/pypa/sampleproject
Author: Serly Armeliana Delvi
Author-email: delviserly354@example.com
License: UNKNOWN
Project-URL: Bug Tracker, https://github.com/pypa/sampleproject/issues
Platform: UNKNOWN
Classifier: Programming Language :: Python :: 3
Classifier: License :: OSI Approved :: MIT License
Classifier: Operating System :: OS Independent
Requires-Python: >=3.6
License-File: LICENSE
